Scripts/__init__.py
J_12_Spotify_recommendation-0.1.8.dist-info/METADATA
J_12_Spotify_recommendation-0.1.8.dist-info/WHEEL
J_12_Spotify_recommendation-0.1.8.dist-info/top_level.txt
J_12_Spotify_recommendation-0.1.8.dist-info/RECORD
